[
  {
    "name":"ABC",
    "date":"2020-07-20",
    "amount":220
  },
  {
    "name":"XYZ",
    "date":"2020-07-10",
    "amount":133
  },
  {
    "name":"ABC",
    "date":"2020-07-22",
    "amount":116
  },
  {
    "name":"ABC",
    "date":"2020-08-18",
    "amount":120
  },
  {
    "name":"XYZ",
    "date":"2020-08-10",
    "amount":63
  },
  {
    "name":"XYZ",
    "date":"2020-08-12",
    "amount":103
  },
  {
    "name":"ABC",
    "date":"2020-09-22",
    "amount":20
  },
  {
    "name":"ABC",
    "date":"2020-09-30",
    "amount":201
  },
  {
    "name":"XYZ",
    "date":"2020-09-10",
    "amount":420
  },
  {
    "name":"XYZ",
    "date":"2020-09-11",
    "amount":328
  }
]